hamlang/__init__.py
hamlang/__main__.py
hamlang/hamlang.py
hamlang-0.0.1.dist-info/LICENSE
hamlang-0.0.1.dist-info/METADATA
hamlang-0.0.1.dist-info/WHEEL
hamlang-0.0.1.dist-info/entry_points.txt
hamlang-0.0.1.dist-info/top_level.txt
hamlang-0.0.1.dist-info/RECORD
