Metadata-Version: 2.1
Name: hamlang
Version: 0.0.1
Summary: 그냥 히읗이 많이 들어간 언어입니다.
Home-page: https://github.com/HshMaker/hamlang
Author: HshMaker
Author-email: hshmakerss@gmail.com
Keywords: hamlang,hshmaker,Esolang
Classifier: License :: OSI Approved :: MIT License
Classifier: Programming Language :: Python :: 3.6
Classifier: Programming Language :: Python :: 3.7
Classifier: Programming Language :: Python :: 3.8
Classifier: Programming Language :: Python :: 3.9
Requires-Python: >=3.6
License-File: LICENSE
